README.md
setup.py
google_trends_api/__init__.py
google_trends_api/_api.py
google_trends_api/constants.py
google_trends_api/utils.py
google_trends_api.egg-info/PKG-INFO
google_trends_api.egg-info/SOURCES.txt
google_trends_api.egg-info/dependency_links.txt
google_trends_api.egg-info/requires.txt
google_trends_api.egg-info/top_level.txt