Metadata-Version: 2.1
Name: google-trends-api
Version: 2.2.5
Summary: Async python wrapper for google trends api
Home-page: UNKNOWN
Author: Magicalbomb
Author-email: 17826800084g@gmail.com
License: MIT
Platform: UNKNOWN
